zennix/__init__.py
zennix/cli.py
zennix/version.py
zennix/commands/__init__.py
zennix/commands/generate.py
zennix/commands/scan.py
zennix/core/__init__.py
zennix/core/generator/readme.py
zennix/core/models/project_metadata.py
zennix/core/scanner/project_scanner.py
zennix/core/scanner/folder/__init__.py
zennix/core/scanner/folder/base.py
zennix/core/scanner/folder/config.py
zennix/core/scanner/folder/result.py
zennix/core/utils/__init__.py
zennix/core/utils/file_ops.py
zennix/core/utils/logger.py
zennix/core/utils/llm/__init__.py
zennix/core/utils/llm/groq_client.py
zennix-0.1.0.dist-info/licenses/LICENSE
zennix-0.1.0.dist-info/METADATA
zennix-0.1.0.dist-info/WHEEL
zennix-0.1.0.dist-info/entry_points.txt
zennix-0.1.0.dist-info/top_level.txt
zennix-0.1.0.dist-info/RECORD
