Metadata-Version: 2.4
Name: Zennix
Version: 0.1.0
Summary: Zennix: AI-powered automation for project documentation and scaffolding
Author-email: Gopal Goyal <goyal11.gopal@gmail.com>
License-Expression: MIT
Project-URL: Homepage, https://github.com/gopal-goyal/zennix
Project-URL: Repository, https://github.com/gopal-goyal/zennix
Classifier: Development Status :: 3 - Alpha
Classifier: Intended Audience :: Developers
Classifier: Topic :: Software Development :: Documentation
Classifier: Topic :: Software Development :: Testing
Classifier: Topic :: Utilities
Classifier: Programming Language :: Python
Classifier: Programming Language :: Python :: 3.11
Classifier: Operating System :: OS Independent
Classifier: Environment :: Console
Requires-Python: >=3.11
License-File: LICENSE
Requires-Dist: typer>=0.15.2
Requires-Dist: groq>=0.22.0
Dynamic: license-file
